cl_simulator/__init__.py
cl_simulator/server.py
cl_simulator/topology_utils.py
cl_simulator/workerclass.py
cl_simulator/workerhandler.py
cl_simulator-0.0.1.dist-info/LICENSE
cl_simulator-0.0.1.dist-info/METADATA
cl_simulator-0.0.1.dist-info/WHEEL
cl_simulator-0.0.1.dist-info/top_level.txt
cl_simulator-0.0.1.dist-info/RECORD
