Metadata-Version: 2.1
Name: cl-simulator
Version: 0.0.1
Summary: python simulator for Collaborative Deep Learning
Home-page: https://github.com/sattviksahai/Collaborative-Learning-Simulator
Author: Sattvik Sahai
Author-email: sattviksahai24@gmail.com
License: UNKNOWN
Platform: UNKNOWN
Classifier: Programming Language :: Python :: 3
Classifier: License :: OSI Approved :: MIT License
Classifier: Operating System :: OS Independent
Requires-Python: >=3.6
